{"firstDate":"13 Junho 2019","lastUpdate":"20190701T135841.000Z","numberOfWars":10,"stats":[{"name":"tiagofl","wins":8},{"name":"Tó Nelson","wins":8},{"name":"XANDE","wins":8},{"name":"aspeçada7","wins":8},{"name":"odagrom","wins":8},{"name":"Vasc0","wins":8},{"name":"zeca","wins":8},{"name":"TrueFast","wins":7},{"name":"mad4win","wins":7},{"name":"Ja te f*di","wins":7},{"name":"Vitor Maia","wins":7},{"name":"tugasempre","wins":7},{"name":"Hornpower","wins":6},{"name":"escavaca bacias","wins":6},{"name":"WEclashED","wins":6},{"name":"bmc","wins":6},{"name":"Paulo","wins":6},{"name":"Quintanilha","wins":6},{"name":"trevo-escocia","wins":6},{"name":"tygerwoods","wins":6},{"name":"oliveira1113","wins":6},{"name":"✌Pinheiro ✌","wins":5},{"name":"Clarity","wins":5},{"name":"guiWall","wins":5},{"name":"Migas","wins":5},{"name":"Carpinteiro","wins":5},{"name":"cmppa","wins":5},{"name":"$marco$","wins":5},{"name":"fão game play","wins":5},{"name":"MultiAlexR1","wins":5},{"name":"Joel (PORTUGAL)","wins":5},{"name":"Pi100PÉ","wins":5},{"name":"Svetlana","wins":5},{"name":"Punker","wins":4},{"name":"⚡️⚡️tanisca⚡️⚡️","wins":4},{"name":"Marko","wins":4},{"name":"Dogas","wins":4},{"name":"Ortega","wins":4},{"name":"mira punk","wins":4},{"name":"muck4mept","wins":4},{"name":"JotaEle","wins":3},{"name":"CARLHO","wins":3},{"name":"xivox","wins":2},{"name":"ricardoflip","wins":2},{"name":"Rúben Costa","wins":2},{"name":"D_D EASY","wins":2},{"name":"Chapinha","wins":1},{"name":"closer love","wins":1},{"name":"Bosscross","wins":1},{"name":"DaMiR04","wins":1},{"name":"redrod77","wins":0},{"name":"MOTA_PT","wins":0},{"name":"Rique","wins":0}]}